MANIFEST.in
README.md
setup.py
django_pinpayments.egg-info/PKG-INFO
django_pinpayments.egg-info/SOURCES.txt
django_pinpayments.egg-info/dependency_links.txt
django_pinpayments.egg-info/not-zip-safe
django_pinpayments.egg-info/requires.txt
django_pinpayments.egg-info/top_level.txt
pinpayments/__init__.py
pinpayments/admin.py
pinpayments/exceptions.py
pinpayments/models.py
pinpayments/objects.py
pinpayments/utils.py
pinpayments/migrations/0001_initial.py
pinpayments/migrations/__init__.py
pinpayments/templates/pinpayments/pin_form.html
pinpayments/templates/pinpayments/pin_headers.html
pinpayments/templatetags/__init__.py
pinpayments/templatetags/pin_payment_tags.py
pinpayments/tests/__init__.py
pinpayments/tests/models.py
pinpayments/tests/templatetags.py