Metadata-Version: 1.1
Name: django-pinpayments
Version: 1.1.0
Summary: Tools for easily adding pin.net.au payment processing to your Django proejct
Home-page: http://github.com/rossp/django-pinpayments
Author: Ross Poulton
Author-email: ross@rossp.org
License: BSD
Keywords: django,payments,pinpayments
Platform: UNKNOWN
Classifier: Programming Language :: Python
Classifier: Topic :: Software Development :: Libraries :: Python Modules
Classifier: Framework :: Django
Classifier: Environment :: Web Environment
Classifier: Operating System :: OS Independent
Classifier: License :: OSI Approved :: BSD License
Classifier: Natural Language :: English
Classifier: Intended Audience :: Developers
Classifier: Development Status :: 3 - Alpha
